rag_scrubber/__init__.py
rag_scrubber/cleaner.py
rag_scrubber-0.1.4.dist-info/METADATA
rag_scrubber-0.1.4.dist-info/WHEEL
rag_scrubber-0.1.4.dist-info/top_level.txt
rag_scrubber-0.1.4.dist-info/RECORD
