Metadata-Version: 2.4
Name: rag-scrubber
Version: 0.1.4
Summary: Auto-removes headers, footers, and noise from PDF text for RAG apps.
Author: MUGESH KUMAR M
Requires-Python: >=3.7
Dynamic: author
Dynamic: description
Dynamic: description-content-type
Dynamic: requires-python
Dynamic: summary
